cpoc/__init__.py
cpoc/__main__.py
cpoc/fcopy.py
cpoc-1.1.dist-info/entry_points.txt
cpoc-1.1.dist-info/LICENSE
cpoc-1.1.dist-info/WHEEL
cpoc-1.1.dist-info/METADATA
cpoc-1.1.dist-info/RECORD
